pacs_chat/__init__.py
pacs_chat/client/__main__.py
pacs_chat/client/chat_client.py
pacs_chat/client/curses_gui.py
pacs_chat/server/__init__.py
pacs_chat/server/__main__.py
pacs_chat/server/handler.py
pacs_chat/server/stores.py
pacschat-1.0.0.dist-info/entry_points.txt
pacschat-1.0.0.dist-info/LICENSE
pacschat-1.0.0.dist-info/WHEEL
pacschat-1.0.0.dist-info/METADATA
pacschat-1.0.0.dist-info/RECORD
