Metadata-Version: 2.1
Name: PacsChat
Version: 1.0.0
Summary: A simple chat server written in Python using asyncio and tcp sockets.
Author-email: Ahmed Munna <munnaa329@gmail.com>
Classifier: License :: OSI Approved :: MIT License
